[
  {
    "name": "ttnn.concat",
    "input_shapes": [
      "tensor<[1,256,16,16,1,f32]>",
      "tensor<[1,256,16,16,1,f32]>",
      "tensor<[1,256,16,16,2,f32]>"
    ],
    "input_layouts": [
      {
        "mapping_from": "(d0, d1, d2, d3, d4)",
        "mapping_to": "(d0 * 65536 + d1 * 256 + d2 * 16 + d3, d4)",
        "memory_config": [
          65536,
          1,
          "f32",
          "dram"
        ]
      },
      {
        "mapping_from": "(d0, d1, d2, d3, d4)",
        "mapping_to": "(d0 * 65536 + d1 * 256 + d2 * 16 + d3, d4)",
        "memory_config": [
          65536,
          1,
          "f32",
          "dram"
        ]
      },
      {
        "mapping_from": "(d0, d1, d2, d3, d4)",
        "mapping_to": "(d0 * 65536 + d1 * 256 + d2 * 16 + d3, d4)",
        "memory_config": [
          65536,
          2,
          "f32",
          "dram"
        ]
      }
    ],
    "attributes": {
      "dim": "4 : si32"
    },
    "output_shapes": [
      "tensor<[1,256,16,16,2,f32]>"
    ],
    "output_layouts": [
      {
        "mapping_from": "(d0, d1, d2, d3, d4)",
        "mapping_to": "(d0 * 65536 + d1 * 256 + d2 * 16 + d3, d4)",
        "memory_config": [
          65536,
          2,
          "f32",
          "dram"
        ]
      }
    ],
    "runs_on_ttnn": "N/A",
    "pcc": "N/A",
    "atol": "N/A"
  },
  {
    "name": "ttnn.concat",
    "input_shapes": [
      "tensor<[1,256,16,32,f32]>",
      "tensor<[1,256,16,32,f32]>",
      "tensor<[1,256,16,64,f32]>"
    ],
    "input_layouts": [
      {
        "mapping_from": "(d0, d1, d2, d3)",
        "mapping_to": "(d0 * 4096 + d1 * 16 + d2, d3)",
        "memory_config": [
          4096,
          32,
          "f32",
          "dram"
        ]
      },
      {
        "mapping_from": "(d0, d1, d2, d3)",
        "mapping_to": "(d0 * 4096 + d1 * 16 + d2, d3)",
        "memory_config": [
          4096,
          32,
          "f32",
          "dram"
        ]
      },
      {
        "mapping_from": "(d0, d1, d2, d3)",
        "mapping_to": "(d0 * 4096 + d1 * 16 + d2, d3)",
        "memory_config": [
          4096,
          64,
          "f32",
          "dram"
        ]
      }
    ],
    "attributes": {
      "dim": "3 : si32"
    },
    "output_shapes": [
      "tensor<[1,256,16,64,f32]>"
    ],
    "output_layouts": [
      {
        "mapping_from": "(d0, d1, d2, d3)",
        "mapping_to": "(d0 * 4096 + d1 * 16 + d2, d3)",
        "memory_config": [
          4096,
          64,
          "f32",
          "dram"
        ]
      }
    ],
    "runs_on_ttnn": "N/A",
    "pcc": "N/A",
    "atol": "N/A"
  }
]
